odoo/addons/hr_employee_product/README.rst
odoo/addons/hr_employee_product/__init__.py
odoo/addons/hr_employee_product/__manifest__.py
odoo/addons/hr_employee_product/i18n/cs_CZ.po
odoo/addons/hr_employee_product/i18n/es.po
odoo/addons/hr_employee_product/i18n/fr.po
odoo/addons/hr_employee_product/i18n/hr_employee_product.pot
odoo/addons/hr_employee_product/i18n/it.po
odoo/addons/hr_employee_product/i18n/pt.po
odoo/addons/hr_employee_product/model/__init__.py
odoo/addons/hr_employee_product/model/product.py
odoo/addons/hr_employee_product/readme/CONTRIBUTORS.rst
odoo/addons/hr_employee_product/readme/DESCRIPTION.rst
odoo/addons/hr_employee_product/readme/USAGE.rst
odoo/addons/hr_employee_product/security/product_security.xml
odoo/addons/hr_employee_product/static/description/icon.png
odoo/addons/hr_employee_product/static/description/index.html
odoo/addons/hr_employee_product/tests/__init__.py
odoo/addons/hr_employee_product/tests/test_hr_employee_product.py
odoo/addons/hr_employee_product/view/product.xml
odoo12_addon_hr_employee_product-12.0.1.0.1.dist-info/METADATA
odoo12_addon_hr_employee_product-12.0.1.0.1.dist-info/WHEEL
odoo12_addon_hr_employee_product-12.0.1.0.1.dist-info/top_level.txt
odoo12_addon_hr_employee_product-12.0.1.0.1.dist-info/RECORD
